polyhex/__init__.py
polyhex/assets/loaders.py
polyhex/objects/__init__.py
polyhex/objects/decorators.py
polyhex/objects/edges.py
polyhex/objects/hexagons.py
polyhex/objects/nodes.py
polyhex/objects/polyhexes.py
polyhex/objects/exporters/__init__.py
polyhex/objects/exporters/pyg_exporter.py
polyhex/objects/graphs/__init__.py
polyhex/objects/graphs/graphs_module.py
polyhex/utilities/__init__.py
polyhex/utilities/utils.py
polyhex-0.1.3.dist-info/licenses/LICENSE
polyhex-0.1.3.dist-info/METADATA
polyhex-0.1.3.dist-info/WHEEL
polyhex-0.1.3.dist-info/top_level.txt
polyhex-0.1.3.dist-info/RECORD
