Metadata-Version: 2.4
Name: polyhex
Version: 0.1.3
Summary: A small example package
Author-email: Emilien Valat <emilienvalat@gmail.com>
Classifier: Programming Language :: Python :: 3
Classifier: License :: OSI Approved :: MIT License
Classifier: Operating System :: OS Independent
Requires-Python: >=3.11
License-File: LICENSE
Requires-Dist: matplotlib
Requires-Dist: numpy
Requires-Dist: scipy
Requires-Dist: torch
Requires-Dist: torch_geometric
Dynamic: license-file
